NBIN/errors.py
NBIN/nbin.py
NBIN/nbin.pyi
NBIN/types.py
NBIN-1.2.dist-info/LICENSE.txt
NBIN-1.2.dist-info/METADATA
NBIN-1.2.dist-info/WHEEL
NBIN-1.2.dist-info/top_level.txt
NBIN-1.2.dist-info/RECORD
