Metadata-Version: 2.1
Name: NBIN
Version: 1.2
Summary: Official library for working with the BIN file format
Author-email: Markada <markada.py@gmail.com>
License: MIT License
Keywords: markada,NBIN,file,storage,HisOS
Classifier: Development Status :: 5 - Production/Stable
Classifier: Environment :: Console
Classifier: Intended Audience :: Developers
Classifier: License :: OSI Approved :: MIT License
Classifier: Natural Language :: English
Classifier: Programming Language :: Python :: 3
Classifier: Topic :: File Formats
Classifier: Typing :: Typed
Requires-Python: >=3.11
License-File: LICENSE.txt
